{
  "tileId": "14_-17",
  "tileSize": 10.0,
  "origin": {
    "x": 140.0,
    "z": -170.0
  },
  "bounds": {},
  "version": 1,
  "buildings": [],
  "roads": [
    {
      "id": "osm_way_351451018",
      "points": [
        {
          "x": 143.532,
          "z": -169.751
        },
        {
          "x": 142.504,
          "z": -169.592
        },
        {
          "x": 143.407,
          "z": -164.872
        }
      ],
      "highway": "footway",
      "width": 2.0
    },
    {
      "id": "osm_way_872354812",
      "points": [
        {
          "x": 140.758,
          "z": -164.264
        },
        {
          "x": 140.907,
          "z": -164.295
        },
        {
          "x": 143.407,
          "z": -164.872
        }
      ],
      "highway": "footway",
      "width": 2.0
    },
    {
      "id": "osm_way_872354813",
      "points": [
        {
          "x": 143.407,
          "z": -164.872
        },
        {
          "x": 147.284,
          "z": -165.981
        }
      ],
      "highway": "footway",
      "width": 2.0
    },
    {
      "id": "osm_way_1384155197",
      "points": [
        {
          "x": 143.938,
          "z": -161.316
        },
        {
          "x": 143.407,
          "z": -164.872
        }
      ],
      "highway": "footway",
      "width": 2.0
    }
  ],
  "water": [],
  "greens": []
}