{
  "tileId": "3_-39",
  "tileSize": 10.0,
  "origin": {
    "x": 30.0,
    "z": -390.0
  },
  "bounds": {},
  "version": 1,
  "buildings": [
    {
      "id": "osm_way_108726402",
      "footprint": [
        {
          "x": 33.513,
          "z": -374.438
        },
        {
          "x": 32.474,
          "z": -376.535
        },
        {
          "x": 38.389,
          "z": -380.265
        },
        {
          "x": 33.346,
          "z": -388.672
        },
        {
          "x": 28.317,
          "z": -385.494
        },
        {
          "x": 27.008,
          "z": -387.941
        },
        {
          "x": 25.388,
          "z": -391.261
        },
        {
          "x": 31.474,
          "z": -395.343
        },
        {
          "x": 32.828,
          "z": -393.373
        },
        {
          "x": 36.86,
          "z": -396.091
        },
        {
          "x": 35.505,
          "z": -397.984
        },
        {
          "x": 44.619,
          "z": -403.946
        },
        {
          "x": 57.344,
          "z": -384.649
        },
        {
          "x": 48.102,
          "z": -379.001
        },
        {
          "x": 47.026,
          "z": -380.766
        },
        {
          "x": 42.927,
          "z": -378.06
        },
        {
          "x": 44.03,
          "z": -376.128
        },
        {
          "x": 35.349,
          "z": -370.291
        }
      ],
      "height": 34.0,
      "levels": 6,
      "type": "apartments"
    }
  ],
  "roads": [],
  "water": [],
  "greens": []
}