{
  "tileId": "6_-13",
  "tileSize": 10.0,
  "origin": {
    "x": 60.0,
    "z": -130.0
  },
  "bounds": {},
  "version": 1,
  "buildings": [
    {
      "id": "osm_way_185952649",
      "footprint": [
        {
          "x": 62.251,
          "z": -119.903
        },
        {
          "x": 62.928,
          "z": -119.913
        },
        {
          "x": 62.514,
          "z": -120.454
        },
        {
          "x": 62.142,
          "z": -121.239
        },
        {
          "x": 62.076,
          "z": -122.118
        },
        {
          "x": 62.198,
          "z": -123.128
        },
        {
          "x": 62.788,
          "z": -124.107
        },
        {
          "x": 63.661,
          "z": -124.703
        },
        {
          "x": 64.622,
          "z": -124.841
        },
        {
          "x": 65.785,
          "z": -127.544
        },
        {
          "x": 62.836,
          "z": -128.831
        },
        {
          "x": 62.952,
          "z": -129.096
        },
        {
          "x": 67.098,
          "z": -137.727
        },
        {
          "x": 90.644,
          "z": -126.408
        },
        {
          "x": 88.758,
          "z": -110.754
        },
        {
          "x": 62.23,
          "z": -110.831
        }
      ],
      "height": 32.0,
      "levels": 6,
      "type": "apartments"
    }
  ],
  "roads": [],
  "water": [],
  "greens": []
}