{
  "tileId": "40_-8",
  "tileSize": 10.0,
  "origin": {
    "x": 400.0,
    "z": -80.0
  },
  "bounds": {},
  "version": 1,
  "buildings": [
    {
      "id": "osm_way_141392512",
      "footprint": [
        {
          "x": 375.448,
          "z": -76.615
        },
        {
          "x": 375.877,
          "z": -78.998
        },
        {
          "x": 373.398,
          "z": -79.554
        },
        {
          "x": 374.583,
          "z": -85.092
        },
        {
          "x": 377.42,
          "z": -84.585
        },
        {
          "x": 377.697,
          "z": -86.792
        },
        {
          "x": 377.672,
          "z": -89.094
        },
        {
          "x": 383.577,
          "z": -89.366
        },
        {
          "x": 383.48,
          "z": -88.945
        },
        {
          "x": 396.667,
          "z": -89.552
        },
        {
          "x": 396.766,
          "z": -90.106
        },
        {
          "x": 402.67,
          "z": -90.277
        },
        {
          "x": 402.872,
          "z": -82.535
        },
        {
          "x": 401.407,
          "z": -72.2
        },
        {
          "x": 404.971,
          "z": -69.956
        },
        {
          "x": 409.115,
          "z": -67.335
        },
        {
          "x": 407.926,
          "z": -90.827
        },
        {
          "x": 442.572,
          "z": -92.548
        },
        {
          "x": 443.85,
          "z": -65.408
        },
        {
          "x": 442.848,
          "z": -65.437
        },
        {
          "x": 443.083,
          "z": -62.397
        },
        {
          "x": 444.043,
          "z": -62.502
        },
        {
          "x": 445.157,
          "z": -39.412
        },
        {
          "x": 436.792,
          "z": -43.643
        },
        {
          "x": 428.815,
          "z": -47.601
        },
        {
          "x": 409.672,
          "z": -57.052
        },
        {
          "x": 409.345,
          "z": -64.885
        },
        {
          "x": 404.334,
          "z": -68.033
        },
        {
          "x": 400.587,
          "z": -70.391
        },
        {
          "x": 396.983,
          "z": -63.429
        },
        {
          "x": 391.671,
          "z": -65.949
        },
        {
          "x": 391.734,
          "z": -66.559
        },
        {
          "x": 380.213,
          "z": -72.16
        },
        {
          "x": 379.925,
          "z": -71.842
        },
        {
          "x": 374.651,
          "z": -74.484
        }
      ],
      "height": 9.0,
      "levels": 3,
      "type": "civic"
    }
  ],
  "roads": [
    {
      "id": "osm_way_962624242",
      "points": [
        {
          "x": 404.971,
          "z": -69.956
        },
        {
          "x": 406.617,
          "z": -82.123
        }
      ],
      "highway": "service",
      "width": 4.0
    }
  ],
  "water": [],
  "greens": []
}