{
  "tileId": "31_22",
  "tileSize": 10.0,
  "origin": {
    "x": 310.0,
    "z": 220.0
  },
  "bounds": {},
  "version": 1,
  "buildings": [
    {
      "id": "osm_way_97667645",
      "footprint": [
        {
          "x": 318.429,
          "z": 220.926
        },
        {
          "x": 318.202,
          "z": 223.19
        },
        {
          "x": 313.169,
          "z": 222.488
        },
        {
          "x": 313.332,
          "z": 220.056
        },
        {
          "x": 306.917,
          "z": 218.929
        },
        {
          "x": 306.994,
          "z": 220.042
        },
        {
          "x": 302.846,
          "z": 220.945
        },
        {
          "x": 302.391,
          "z": 218.18
        },
        {
          "x": 293.565,
          "z": 216.431
        },
        {
          "x": 276.259,
          "z": 248.54
        },
        {
          "x": 287.146,
          "z": 258.387
        },
        {
          "x": 331.989,
          "z": 249.4
        },
        {
          "x": 329.575,
          "z": 233.68
        },
        {
          "x": 330.002,
          "z": 228.551
        },
        {
          "x": 324.571,
          "z": 227.697
        },
        {
          "x": 325.377,
          "z": 222.141
        }
      ],
      "height": 26.5,
      "levels": 7,
      "type": "apartments"
    }
  ],
  "roads": [],
  "water": [],
  "greens": []
}