{
  "tileId": "-14_-48",
  "tileSize": 10.0,
  "origin": {
    "x": -140.0,
    "z": -480.0
  },
  "bounds": {},
  "version": 1,
  "buildings": [
    {
      "id": "osm_way_192914511",
      "footprint": [
        {
          "x": -151.243,
          "z": -484.124
        },
        {
          "x": -145.365,
          "z": -486.598
        },
        {
          "x": -130.201,
          "z": -461.944
        },
        {
          "x": -128.669,
          "z": -459.548
        },
        {
          "x": -126.665,
          "z": -456.077
        },
        {
          "x": -123.609,
          "z": -457.823
        },
        {
          "x": -115.065,
          "z": -463.062
        },
        {
          "x": -115.341,
          "z": -463.434
        },
        {
          "x": -113.898,
          "z": -464.297
        },
        {
          "x": -117.642,
          "z": -470.213
        },
        {
          "x": -137.4,
          "z": -502.643
        },
        {
          "x": -148.408,
          "z": -498.016
        },
        {
          "x": -155.836,
          "z": -494.891
        }
      ],
      "height": 30.5,
      "levels": 7,
      "type": "apartments"
    }
  ],
  "roads": [],
  "water": [],
  "greens": []
}