{
  "tileId": "-14_-17",
  "tileSize": 10.0,
  "origin": {
    "x": -140.0,
    "z": -170.0
  },
  "bounds": {},
  "version": 1,
  "buildings": [],
  "roads": [
    {
      "id": "osm_way_690563351",
      "points": [
        {
          "x": -138.178,
          "z": -160.338
        },
        {
          "x": -138.003,
          "z": -161.825
        },
        {
          "x": -138.618,
          "z": -163.582
        }
      ],
      "highway": "service",
      "width": 4.0
    },
    {
      "id": "osm_way_690563353",
      "points": [
        {
          "x": -128.835,
          "z": -167.531
        },
        {
          "x": -132.311,
          "z": -168.038
        },
        {
          "x": -134.938,
          "z": -168.63
        },
        {
          "x": -137.435,
          "z": -168.619
        },
        {
          "x": -139.486,
          "z": -168.211
        }
      ],
      "highway": "service",
      "width": 4.0
    },
    {
      "id": "osm_way_690563354",
      "points": [
        {
          "x": -127.07,
          "z": -164.386
        },
        {
          "x": -135.176,
          "z": -161.185
        }
      ],
      "highway": "service",
      "width": 4.0
    }
  ],
  "water": [],
  "greens": []
}