{
  "tileId": "7_-25",
  "tileSize": 10.0,
  "origin": {
    "x": 70.0,
    "z": -250.0
  },
  "bounds": {},
  "version": 1,
  "buildings": [],
  "roads": [
    {
      "id": "osm_way_347060529",
      "points": [
        {
          "x": 72.388,
          "z": -241.787
        },
        {
          "x": 72.442,
          "z": -252.249
        }
      ],
      "highway": "pedestrian",
      "width": 5.0,
      "name": "Georg-Coch-Platz"
    },
    {
      "id": "osm_way_347060535",
      "points": [
        {
          "x": 72.351,
          "z": -239.742
        },
        {
          "x": 72.388,
          "z": -241.787
        }
      ],
      "highway": "steps",
      "width": 2.0
    },
    {
      "id": "osm_way_351541100",
      "points": [
        {
          "x": 77.536,
          "z": -244.563
        },
        {
          "x": 73.455,
          "z": -247.027
        },
        {
          "x": 77.656,
          "z": -250.454
        }
      ],
      "highway": "service",
      "width": 4.0
    }
  ],
  "water": [],
  "greens": []
}