{
  "tileId": "23_37",
  "tileSize": 10.0,
  "origin": {
    "x": 230.0,
    "z": 370.0
  },
  "bounds": {},
  "version": 1,
  "buildings": [
    {
      "id": "osm_way_97533491",
      "footprint": [
        {
          "x": 234.923,
          "z": 374.265
        },
        {
          "x": 236.699,
          "z": 373.83
        },
        {
          "x": 237.765,
          "z": 374.45
        },
        {
          "x": 239.964,
          "z": 373.689
        },
        {
          "x": 240.699,
          "z": 372.49
        },
        {
          "x": 240.517,
          "z": 371.008
        },
        {
          "x": 245.314,
          "z": 369.549
        },
        {
          "x": 244.831,
          "z": 367.917
        },
        {
          "x": 248.257,
          "z": 366.667
        },
        {
          "x": 243.898,
          "z": 355.337
        },
        {
          "x": 223.762,
          "z": 361.912
        },
        {
          "x": 226.584,
          "z": 371.046
        },
        {
          "x": 229.298,
          "z": 370.117
        },
        {
          "x": 230.575,
          "z": 373.898
        },
        {
          "x": 227.795,
          "z": 374.759
        },
        {
          "x": 230.865,
          "z": 384.209
        },
        {
          "x": 237.328,
          "z": 382.225
        }
      ],
      "height": 18.0,
      "levels": 6,
      "type": "apartments"
    }
  ],
  "roads": [],
  "water": [],
  "greens": []
}