{
  "tileId": "-44_-10",
  "tileSize": 10.0,
  "origin": {
    "x": -440.0,
    "z": -100.0
  },
  "bounds": {},
  "version": 1,
  "buildings": [],
  "roads": [
    {
      "id": "osm_way_867322308",
      "points": [
        {
          "x": -429.294,
          "z": -99.514
        },
        {
          "x": -432.112,
          "z": -99.053
        },
        {
          "x": -431.311,
          "z": -98.105
        }
      ],
      "highway": "pedestrian",
      "width": 5.0
    }
  ],
  "water": [],
  "greens": []
}